flask_profiling/__init__.py
flask_profiling/api.py
flask_profiling/backends.py
flask_profiling/decorators.py
flask_profiling/ext.py
flask_profiling/models.py
flask_profiling/static/dist/index.html
flask_profiling/static/dist/css/main.css
flask_profiling/static/dist/fonts/glyphicons-halflings-regular.eot
flask_profiling/static/dist/fonts/glyphicons-halflings-regular.svg
flask_profiling/static/dist/fonts/glyphicons-halflings-regular.ttf
flask_profiling/static/dist/fonts/glyphicons-halflings-regular.woff
flask_profiling/static/dist/images/python-flask.png
flask_profiling/static/dist/js/main.js
flask_profiling/static/dist/js/settings.js
flask_profiling/static/dist/js/vendor.js
flask_profiling-0.3.2.dist-info/LICENSE
flask_profiling-0.3.2.dist-info/METADATA
flask_profiling-0.3.2.dist-info/WHEEL
flask_profiling-0.3.2.dist-info/top_level.txt
flask_profiling-0.3.2.dist-info/RECORD
