Metadata-Version: 2.1
Name: flask-profiling
Version: 0.3.2
Summary: A simple web UI for flask to profile the apis
Home-page: https://github.com/huangxiaohen2738/flask-profiling
Author: huangxiaohen2738
Author-email: huangxiaohen2738@gmail.com
License: Apache License
Requires-Dist: flask
Requires-Dist: flask-admin
Requires-Dist: flask-httpauth
Requires-Dist: itsdangerous
Requires-Dist: jinja2
Requires-Dist: ldap
Requires-Dist: markupSafe
Requires-Dist: pymysql
Requires-Dist: sqlalchemy
Requires-Dist: werkzeug
